[
    {
        "settingId": "inlineChat.acceptedOrDiscardBeforeSave",
        "desc": " Whether pending inline chat sessions prevent saving.",
        "setting": {
            "inlineChat.acceptedOrDiscardBeforeSave": true
        }
    },
    {
        "settingId": "inlineChat.accessibleDiffView",
        "desc": " Whether the inline chat also renders an accessible diff viewer for its changes.\n  - auto: The accessible diff viewer is based on screen reader mode being enabled.\n  - on: The accessible diff viewer is always enabled.\n  - off: The accessible diff viewer is never enabled.",
        "setting": {
            "inlineChat.accessibleDiffView": "auto"
        }
    },
    {
        "settingId": "inlineChat.finishOnType",
        "desc": " Whether to finish an inline chat session when typing outside of changed regions.",
        "setting": {
            "inlineChat.finishOnType": false
        }
    },
    {
        "settingId": "inlineChat.holdToSpeech",
        "desc": " Whether holding the inline chat keybinding will automatically enable speech recognition.",
        "setting": {
            "inlineChat.holdToSpeech": true
        }
    },
    {
        "settingId": "inlineChat.mode",
        "desc": " Configure if changes crafted with inline chat are applied directly to the document or are previewed first.\n  - live: Changes are applied directly to the document, can be highlighted via inline diffs, and accepted/discarded by hunks. Ending a session will keep the changes.\n  - preview: Changes are previewed only and need to be accepted via the apply button. Ending a session will discard the changes.",
        "setting": {
            "inlineChat.mode": "live"
        }
    }
]